test/__init__.py
test/test_calc.py
yopycalc/__init__.py
yopycalc/calc.py
yopycalc-0.0.4.8.dist-info/METADATA
yopycalc-0.0.4.8.dist-info/WHEEL
yopycalc-0.0.4.8.dist-info/top_level.txt
yopycalc-0.0.4.8.dist-info/RECORD
