Metadata-Version: 2.1
Name: yopycalc
Version: 0.0.4.8
Summary: yopycalc python module
Home-page: https://github.com/ravindra-rao/setuptoolsdemo.git
Author: yobro
Author-email: contact@yobro.com
Classifier: Programming Language :: Python :: 3
Classifier: Operating System :: OS Independent
Requires-Dist: pandas
Requires-Dist: pytest
